{"AppDelegate":["application","applicationWillResignActive","applicationDidEnterBackground","applicationWillEnterForeground","applicationDidBecomeActive","applicationWillTerminate"],"HeadTransform":["translation","forwardVector","upVector","rightVector","quaternion","eulerAngles"],"Vector3d":["zero","set","set","setComponent","normalize","length","scale","largestAbsComponent","cross","dot","ortho","sub"],"CardboadDeviceParams":[],"GLStateBackup":["addTrackedVertexAttribute","clearTrackedVertexAttributes","readFromGL","writeToGL","readFromGL","writeToGL"],"GLUtils":["clamp","BUFFER_OFFSET","GLLinkProgram","GLCheckForError","GLCompileFromString","GLCompileShaderFromFile","GLValidateProgram"],"ScreenParams":["orientationAwareSize","sizeFixedToPortrait","width","height","borderSizeInMeters","widthInMeters","heightInMeters","pixelsPerInch"],"HeaderTracker":["getLastHeadView","isReady","startTracking","stopTracking","updateDeviceOrientation","GetRotateEulerMatrix","GLMatrixFromRotationMatrix"],"FieldOfView":["toPerspectiveMatrix"],"GameViewController":["viewDidLoad","setupRendererWithView","prepareNewFrameWithHeadViewMatrix","drawEyeWithEye","shutdownRendererWithView","rendererDidChangeSize","finishFrameWithViewportRect","loadShaders","didReceiveMemoryWarning","tearDownGL"],"Distortion":["setCoefficients","distortionFactor","distort","distortInverse"],"CSViewController":["eyeViewMatrix","perspectiveMatrixWithZNear","setup","viewDidLoad","glkView","update","drawFrameWithHeadTransform","calculateFrameParametersWithHeadTransform","finishFrameWithViewPort","updateEyeFovs","updateUndistortedFOVAndViewport","virtualEyeToScreenDistance","getFrameParameters"],"SO3Util":["so3FromTwoVecN","rotationPiAboutAxis","rodriguesSo3Exp","so3FromMu","muFromSO3"],"Eye":["calculatePerspective"],"HeadMountedDisplay":[],"Viewport":["setViewport","setGLViewport","setGLScissor","toCGRect"]}